arlogger/__init__.py
arlogger/main.py
arlogger-1.0.2.dist-info/METADATA
arlogger-1.0.2.dist-info/WHEEL
arlogger-1.0.2.dist-info/top_level.txt
arlogger-1.0.2.dist-info/RECORD
