Metadata-Version: 2.1
Name: arlogger
Version: 1.0.2
Summary: Send urgent and daily log files to a remote server
Home-page: https://bitbucket.org/asrturk/ar-ai-logger/src/master/
Author: Mirza ATLI
Author-email: mirza.atli@ardictech.com
License: MIT
Classifier: License :: OSI Approved :: MIT License
Classifier: Programming Language :: Python :: 3
Classifier: Programming Language :: Python :: 3.9
Requires-Dist: requests
